email_utils/__init__.py
email_utils/email_generator.py
email_utils/email_validator.py
tests/__init__.py
tests/test_email_generator.py
tests/test_email_validator.py
email_utils_PyWendi-0.1.dist-info/LICENCE
email_utils_PyWendi-0.1.dist-info/METADATA
email_utils_PyWendi-0.1.dist-info/WHEEL
email_utils_PyWendi-0.1.dist-info/top_level.txt
email_utils_PyWendi-0.1.dist-info/RECORD
